pyqt_animated_line_edit/__init__.py
pyqt_animated_line_edit/animated_line_edit.py
pyqt_animated_line_edit-1.0.1.dist-info/LICENSE
pyqt_animated_line_edit-1.0.1.dist-info/METADATA
pyqt_animated_line_edit-1.0.1.dist-info/WHEEL
pyqt_animated_line_edit-1.0.1.dist-info/top_level.txt
pyqt_animated_line_edit-1.0.1.dist-info/RECORD
