Metadata-Version: 2.1
Name: pyqt-animated-line-edit
Version: 1.0.1
Summary: An animated version of the QLineEdit widget for PyQt and PySide
Home-page: https://github.com/marcohenning/pyqt-animated-line-edit
Author: Marco Henning
License: MIT
Keywords: python,pyqt,qt,lineedit
Classifier: Programming Language :: Python :: 3
Classifier: Operating System :: OS Independent
Classifier: License :: OSI Approved :: MIT License
Requires-Python: >=3.7
License-File: LICENSE
Requires-Dist: QtPy>=2.4.1
